{
	"id": "E14000966",
	"title": "Staffordshire Moorlands",
	"elections": {
		"2019": {
			"candidates": [{
				"id": 1303,
				"name": "Karen Bradley",
				"party": { "code": "Con", "title": "Conservative and Unionist Party" },
				"img": "https://static-candidates.democracyclub.org.uk/media/images/5534f7a5b247335574a42e37.png"
			},{
				"id": 4833,
				"name": "Darren Price",
				"party": { "code": "Lab", "title": "Labour Party" },
				"img": "https://static-candidates.democracyclub.org.uk/media/images/images/4833.png"
			},{
				"id": 8867,
				"name": "Andrew Gant",
				"party": { "code": "LD", "title": "Liberal Democrats" },
				"img": "https://static-candidates.democracyclub.org.uk/media/images/images/8867.png"
			},{
				"id": 24927,
				"name": "Doug Rouxel",
				"party": { "code": "Green", "title": "Green Party" },
				"img": "https://static-candidates.democracyclub.org.uk/media/images/images/24927.png"
			}],
			"incumbent": {
				"mp": "Karen Bradley",
				"party": { "code": "Con", "title": "Conservative" }
			}
		},
		"2017": {
			"mp": "Karen Bradley",
			"party": { "code": "Con" },
			"mysoc": "https://www.theyworkforyou.com/mp/24725/karen_bradley/staffordshire_moorlands",
			"electorate": 63260,
			"turnout": 70.6,
			"valid": 44655,
			"spoiled": 84,
			"majority": 10830
		},
		"2015": {
			"mp": "Karen Bradley",
			"party": { "code": "Con", "title": "Conservative" },
			"electorate": 63104,
			"turnout": 67.7,
			"valid": 42587,
			"spoiled": 126,
			"majority": 10174
		}
	}
}