{
	"id": "E14000991",
	"title": "The Cotswolds",
	"demographics": {
		"2015UKIP": 10.92,
		"leave": 47.8,
		"age18-29": 10.72,
		"withdegree": 21.18
	},
	"elections": {
		"2019-12-12": {
			"type": "general",
			"candidates": [{
				"id": 3809,
				"name": "Geoffrey Robert Clifton-Brown",
				"party": { "code": "Con", "title": "Conservative and Unionist Party" },
				"img": "https://static-candidates.democracyclub.org.uk/media/images/5548f7fa84e9778b52be3986.png"
			},{
				"id": 31895,
				"name": "Sabrina Poole",
				"party": { "code": "Green", "title": "Green Party" },
				"img": "https://static-candidates.democracyclub.org.uk/media/images/images/31895_TZJVqoo.png"
			},{
				"id": 34962,
				"name": "Liz Webster",
				"party": { "code": "LD", "title": "Liberal Democrats" },
				"img": "https://static-candidates.democracyclub.org.uk/media/images/images/34962.png"
			},{
				"id": 55255,
				"name": "Alan MacKenzie",
				"party": { "code": "Lab", "title": "Labour Party" },
				"img": "https://static-candidates.democracyclub.org.uk/media/images/images/55255-1b27aa9e-940a-44cd-92a0-f6103d59f845.png"
			}]
		},
		"2017-06-08": {
			"type": "general",
			"mp": "Geoffrey Clifton-Brown",
			"party": { "code": "Con" },
			"electorate": 80449,
			"turnout": { "pc": 74.4, "value": 59829 },
			"valid": 59702,
			"invalid": 127,
			"majority": 25499,
			"candidates": [{
				"name": "Geoffrey Clifton-Brown",
				"party": { "code": "Con", "title": "Conservative" },
				"votes": 36201
			},{
				"name": "Mark Huband",
				"party": { "code": "Lab", "title": "Labour" },
				"votes": 10702
			},{
				"name": "Andrew Gant",
				"party": { "code": "LD", "title": "Liberal Democrat" },
				"votes": 9748
			},{
				"name": "Sabrina Poole",
				"party": { "code": "Green", "title": "Green" },
				"votes": 1747
			},{
				"name": "Chris Harlow",
				"party": { "code": "UKIP", "title": "UK Independence Party" },
				"votes": 1197
			},{
				"name": "James Steel",
				"party": { "code": "Ind", "title": "Independent" },
				"votes": 107
			}]
		},
		"2015-05-07": {
			"type": "general",
			"mp": "Geoffrey Clifton-Brown",
			"party": { "code": "Con", "title": "Conservative" },
			"electorate": 78290,
			"turnout": { "pc":72.6, "value": 56864 },
			"valid": 56667,
			"invalid": 197,
			"majority": 21477
		}
	}
}