{
	"id": "E14000710",
	"title": "Gedling",
	"demographics": {
		"2015UKIP": 14.44,
		"leave": 56.2,
		"age18-29": 13.58,
		"withdegree": 13.99
	},
	"elections": {
		"2019-12-12": {
			"type": "general",
			"candidates": [{
				"id": 1272,
				"name": "Vernon Coaker",
				"party": { "code": "Lab", "title": "Labour Party" },
				"img": "https://static-candidates.democracyclub.org.uk/media/images/553b8ce5a621e036281d5742.png"
			},{
				"id": 4901,
				"name": "Jim Norris",
				"party": { "code": "Green", "title": "Green Party" },
				"img": "https://static-candidates.democracyclub.org.uk/media/images/554800f7202d360b737e0ffa.png"
			},{
				"id": 7411,
				"name": "Anita Prabhakar",
				"party": { "code": "LD", "title": "Liberal Democrats" },
				"img": "https://static-candidates.democracyclub.org.uk/media/images/5548acb09b4dcd1028de1cc0.png"
			},{
				"id": 71449,
				"name": "Graham Hunt",
				"party": { "code": "Brexit", "title": "The Brexit Party" },
				"img": "https://static-candidates.democracyclub.org.uk/media/images/images/71449-780af7e4-64ec-4757-a77f-3569ac88d6be.png"
			},{
				"id": 71450,
				"name": "Tom Randall",
				"party": { "code": "Con", "title": "Conservative and Unionist Party" },
				"img": "https://static-candidates.democracyclub.org.uk/media/images/images/71450.png"
			}]
		},
		"2017-06-08": {
			"type": "general",
			"mp": "Vernon Coaker",
			"party": { "code": "Lab" },
			"electorate": 71223,
			"turnout": { "pc": 72.7, "value": 51765 },
			"valid": 51682,
			"invalid": 83,
			"majority": 4694,
			"candidates": [{
				"name": "Vernon Coaker",
				"party": { "code": "Lab", "title": "Labour" },
				"votes": 26833
			},{
				"name": "Carolyn Abbott",
				"party": { "code": "Con", "title": "Conservative" },
				"votes": 22139
			},{
				"name": "Lee  Waters",
				"party": { "code": "UKIP", "title": "UK Independence Party" },
				"votes": 1143
			},{
				"name": "Robert  Swift",
				"party": { "code": "LD", "title": "Liberal Democrat" },
				"votes": 1052
			},{
				"name": "Rebecca  Connick",
				"party": { "code": "Green", "title": "Green" },
				"votes": 515
			}]
		},
		"2015-05-07": {
			"type": "general",
			"mp": "Vernon Coaker",
			"party": { "code": "Lab", "title": "Labour" },
			"electorate": 70000,
			"turnout": { "pc":68.8, "value": 48143 },
			"valid": 47998,
			"invalid": 145,
			"majority": 2986
		}
	}
}